gpru/__about__.py
gpru/__init__.py
gpru/_client.py
gpru/_logger.py
gpru/exceptions.py
gpru/py.typed
gpru/azure/__init__.py
gpru/azure/_api.py
gpru/azure/_utils.py
gpru/azure/preview_2022_03_01.py
gpru/azure/preview_2022_06_01.py
gpru/azure/preview_2023_03_15.py
gpru/azure/preview_2023_06_01.py
gpru/azure/py.typed
gpru/azure/stable_2022_12_01.py
gpru/azure/stable_2023_05_15.py
gpru/openai/__init__.py
gpru/openai/api.py
gpru/openai/py.typed
gpru-0.3.1.dist-info/METADATA
gpru-0.3.1.dist-info/WHEEL
gpru-0.3.1.dist-info/licenses/LICENSE
gpru-0.3.1.dist-info/RECORD
