Metadata-Version: 2.1
Name: gpru
Version: 0.3.1
Summary: Unofficial Python client library for the OpenAI and Azure OpenAI APIs
Project-URL: Documentation, https://github.com/sincekmori/gpru#readme
Project-URL: Issues, https://github.com/sincekmori/gpru/issues
Project-URL: Source, https://github.com/sincekmori/gpru
Author-email: Shinsuke Mori <sincekmori@gmail.com>
License-Expression: MIT
License-File: LICENSE
Keywords: asyncio,azure,chatgpt,gpt,gpt-3,gpt-4,openai,pydantic
Classifier: Development Status :: 4 - Beta
Classifier: Intended Audience :: Developers
Classifier: License :: OSI Approved :: MIT License
Classifier: Operating System :: OS Independent
Classifier: Programming Language :: Python
Classifier: Programming Language :: Python :: 3 :: Only
Classifier: Programming Language :: Python :: 3.7
Classifier: Programming Language :: Python :: 3.8
Classifier: Programming Language :: Python :: 3.9
Classifier: Programming Language :: Python :: 3.10
Classifier: Programming Language :: Python :: 3.11
Classifier: Programming Language :: Python :: Implementation :: CPython
Classifier: Topic :: Communications :: Chat
Classifier: Topic :: Scientific/Engineering :: Artificial Intelligence
Requires-Python: >=3.7
Requires-Dist: httpx[http2]>=0.24.1
Requires-Dist: pydantic>=2.0.2
Requires-Dist: tenacity>=8.2.2
